loginween/__init__.py
loginween/main.py
loginween/run.py
loginween-0.0.1.dist-info/licenses/LICENSE
loginween-0.0.1.dist-info/METADATA
loginween-0.0.1.dist-info/WHEEL
loginween-0.0.1.dist-info/entry_points.txt
loginween-0.0.1.dist-info/top_level.txt
loginween-0.0.1.dist-info/RECORD
