Metadata-Version: 2.4
Name: loginween
Version: 0.0.1
Summary: LoginWeen
Classifier: License :: OSI Approved :: GNU General Public License v3 (GPLv3)
Classifier: Programming Language :: Python :: 3
Classifier: Programming Language :: Python :: 3.11
Classifier: Operating System :: OS Independent
Requires-Python: >=3.11
License-File: LICENSE
Requires-Dist: flask>=3.1.2
Requires-Dist: flask-login>=0.6.3
Requires-Dist: python-dotenv>=1.1.1
Dynamic: license-file
